zipit/__init__.py
zipit/__main__.py
zipit/cli.py
zipit/zipit.py
zipit-0.0.2.dist-info/LICENSE
zipit-0.0.2.dist-info/METADATA
zipit-0.0.2.dist-info/WHEEL
zipit-0.0.2.dist-info/entry_points.txt
zipit-0.0.2.dist-info/top_level.txt
zipit-0.0.2.dist-info/RECORD
